CHANGELOG.md
mdc/__init__.py
mdc/_version.py
mdc/mdc.py
mdc/resources/iclr-1.0.0.bst
mdc/resources/iclr-1.0.0.sty
mdc/resources/icml-1.0.0.bst
mdc/resources/icml-1.0.0.sty
mdc/resources/neurips-1.0.0.sty
mdc/templates/iclr-1.0.0.tex
mdc/templates/icml-1.0.0.tex
mdc/templates/neurips-1.0.0.tex
mdc/templates/note-1.0.0.tex
mdc/templates/simple-1.0.0.tex
mdc/templates/standalone-1.0.0.tex
mdc/templates/stub-1.0.0.tex
mdc/templates/stylish-1.0.0.tex
shinymdc-9.2.0.dist-info/entry_points.txt
shinymdc-9.2.0.dist-info/LICENSE
shinymdc-9.2.0.dist-info/WHEEL
shinymdc-9.2.0.dist-info/METADATA
shinymdc-9.2.0.dist-info/RECORD
