Metadata-Version: 2.1
Name: shinymdc
Version: 9.2.0
Summary: Tool to compile markdown files to tex/pdf using pandoc, latexmk
Home-page: https://github.com/jayanthkoushik/mdc
License: MIT
Author: Jayanth Koushik
Author-email: jnkoushik@gmail.com
Requires-Python: >=3.7,<4.0
Classifier: Development Status :: 4 - Beta
Classifier: Environment :: Console
Classifier: Intended Audience :: End Users/Desktop
Classifier: License :: OSI Approved :: MIT License
Classifier: Natural Language :: English
Classifier: Operating System :: OS Independent
Classifier: Programming Language :: Python :: 3
Classifier: Programming Language :: Python :: 3.10
Classifier: Programming Language :: Python :: 3.7
Classifier: Programming Language :: Python :: 3.8
Classifier: Programming Language :: Python :: 3.9
Classifier: Topic :: Utilities
Requires-Dist: corgy[colors] (>=4.4,<5.0)
Requires-Dist: typing_extensions (>=4.0,<5.0); python_version < "3.9"
Project-URL: Repository, https://github.com/jayanthkoushik/mdc
